PlasmidHunter/PlasmidHunter.py
PlasmidHunter/__init__.py
PlasmidHunter/functions.py
PlasmidHunter/model/feature_genes.gz
PlasmidHunter/model/guassiannb_model_params.json.gz
plasmidhunter-1.4.dist-info/LICENSE.md
plasmidhunter-1.4.dist-info/METADATA
plasmidhunter-1.4.dist-info/WHEEL
plasmidhunter-1.4.dist-info/entry_points.txt
plasmidhunter-1.4.dist-info/top_level.txt
plasmidhunter-1.4.dist-info/RECORD
