Metadata-Version: 2.1
Name: plasmidhunter
Version: 1.4
Requires-Python: ==3.10.*
License-File: LICENSE.md
Requires-Dist: requests
Requires-Dist: pandas
Requires-Dist: numpy ==1.25.0
Requires-Dist: biopython
Requires-Dist: scikit-learn ==1.3.2
